coveragepy_lcov/__init__.py
coveragepy_lcov/__main__.py
coveragepy_lcov/cli.py
coveragepy_lcov/converter.py
coveragepy_lcov-0.1.2.dist-info/entry_points.txt
coveragepy_lcov-0.1.2.dist-info/LICENSE
coveragepy_lcov-0.1.2.dist-info/WHEEL
coveragepy_lcov-0.1.2.dist-info/METADATA
coveragepy_lcov-0.1.2.dist-info/RECORD
