Metadata-Version: 2.1
Name: coveragepy-lcov
Version: 0.1.2
Summary: A simple .coverage to LCOV converter
Home-page: https://github.com/chaychoong/coveragepy-lcov
Keywords: coverage
Author: Chay Choong
Author-email: chaychoong@gmail.com
Requires-Python: >=3.6.3,<4.0.0
Classifier: Programming Language :: Python :: 3
Classifier: Programming Language :: Python :: 3.10
Classifier: Programming Language :: Python :: 3.7
Classifier: Programming Language :: Python :: 3.8
Classifier: Programming Language :: Python :: 3.9
Requires-Dist: click (>=7.1.2)
Requires-Dist: coverage (>=5.5)
Project-URL: Repository, https://github.com/chaychoong/coveragepy-lcov
